{"name":"IPC::Run","dist":"IPC-Run-0.96","pathname":"T/TO/TODDR/IPC-Run-0.96.tar.gz","target":"IPC::Run","version":"0.96","provides":{"IPC::Run::Win32Pump":{"version":"0.96","file":"lib/IPC/Run/Win32Pump.pm"},"IPC::Run":{"file":"lib/IPC/Run.pm","version":"0.96"},"IPC::Run::Win32IO":{"file":"lib/IPC/Run/Win32IO.pm","version":"0.96"},"IPC::Run::Win32Helper":{"version":"0.96","file":"lib/IPC/Run/Win32Helper.pm"},"IPC::Run::Debug":{"version":"0.96","file":"lib/IPC/Run/Debug.pm"},"IPC::Run::IO":{"version":"0.96","file":"lib/IPC/Run/IO.pm"},"IPC::Run::Timer":{"version":"0.96","file":"lib/IPC/Run/Timer.pm"}}}